[
    {
        "title": "요즘 스타일링",
        "styling_date": "2022.10.04",
        "view_num": 4860,
        "styling_txt": "레터링이 돋보이는 후드 티셔츠와 데님 팬츠를 코디하고 스니커즈로 마무리한 캐주얼 룩",
        "image_url": "https://image.msscdn.net/images/codimap/detail/19025/detail_19025_1_500.jpg?202402142102",
        "item_urls": [
            "https://www.musinsa.com/app/goods/2351592",
            "https://www.musinsa.com/app/goods/2247224",
            "https://www.musinsa.com/app/goods/1334555",
            "https://www.musinsa.com/app/goods/1734820",
            "https://www.musinsa.com/app/goods/1569384"
        ],
        "hashtags": [],
        "style_tag": "캐주얼",
        "item_list": [
            {
                "title": "오버핏 루슈 MA-1 (크림)",
                "big_category": "아우터",
                "small_category": "블루종/MA-1",
                "item_hashtags": [
                    "MA-1",
                    "오버핏",
                    "항공점퍼",
                    "아우터",
                    "22S/S신상품",
                    "블루종"
                ],
                "image_url": "https://image.msscdn.net/images/goods_img/20220210/2351592/2351592_1_500.jpg"
            },
            {
                "title": "World Flower Hoodie [Black]",
                "big_category": "상의",
                "small_category": "후드 티셔츠",
                "item_hashtags": [
                    "오버핏후드티",
                    "오버핏후드",
                    "로고후드",
                    "기모후드",
                    "그래픽",
                    "후드티"
                ],
                "image_url": "https://image.msscdn.net/images/goods_img/20211125/2247224/2247224_1_500.jpg"
            },
            {
                "title": "페이트로 7601 세미와이드핏 크림 데님팬츠",
                "big_category": "바지",
                "small_category": "데님 팬츠",
                "item_hashtags": [
                    "맥우드건데님",
                    "미니멀룩",
                    "와이드데님",
                    "크림데님",
                    "크림진",
                    "와이드",
                    "데님컬렉션",
                    "데님",
                    "기모"
                ],
                "image_url": "https://image.msscdn.net/images/goods_img/20200304/1334555/1334555_16941507645696_500.jpg"
            },
            {
                "title": "서울컬렉션 행당 투명",
                "big_category": "선글라스/안경테",
                "small_category": "안경",
                "item_hashtags": [
                    "utlet",
                    "울렛",
                    "품 구분",
                    "울렛 상품",
                    "신사 스토어 아울렛은 무신사가 엄선한 인기 브랜드 상품을 높은 할인율의 특가로 만날 수 있는 전문관입니다. 스트릿, 캐주얼, 스포츠 패션 부터 럭셔리, 뷰티, 라이프 스타일 브랜드까지 다양한 상품을 언제나 아울렛 전용 혜택으로 제공합니다."
                ],
                "image_url": "https://image.msscdn.net/images/goods_img/20201231/1734820/1734820_17059748064156_500.jpg"
            },
            {
                "title": "포레스트 친환경 런닝화 화이트",
                "big_category": "스니커즈",
                "small_category": "패션스니커즈화",
                "item_hashtags": [
                    "친환경",
                    "캐주얼",
                    "런닝화",
                    "업사이클링",
                    "친환경신발",
                    "심플"
                ],
                "image_url": "https://image.msscdn.net/images/goods_img/20200828/1569384/1569384_16722903544868_500.jpg"
            }
        ]
    },
    {
        "title": "느낌 있는 캐주얼",
        "styling_date": "2022.10.04",
        "view_num": 2431,
        "styling_txt": "컬러 배색이 돋보이는 블루종과 데님 팬츠를 매치하고 숄더백을 더해 완성한 캐주얼 룩",
        "image_url": "https://image.msscdn.net/images/codimap/detail/19024/detail_19024_1_500.jpg?202402142102",
        "item_urls": [
            "https://www.musinsa.com/app/goods/2789895",
            "https://www.musinsa.com/app/goods/2717604",
            "https://www.musinsa.com/app/goods/1481590"
        ],
        "hashtags": [],
        "style_tag": "캐주얼",
        "item_list": [
            {
                "title": "SIDE PANNEL W JACKET BEIGE",
                "big_category": "아우터",
                "small_category": "블루종/MA-1",
                "item_hashtags": [
                    "정판매",
                    "신사 스토어를 포함한 제한된 판매처에서만 구매 가능한 상품입니다."
                ],
                "image_url": "https://image.msscdn.net/images/goods_img/20220914/2789895/2789895_12_500.jpg"
            },
            {
                "title": "[WIDE] Abel Jeans",
                "big_category": "바지",
                "small_category": "데님 팬츠",
                "item_hashtags": [],
                "image_url": "https://image.msscdn.net/images/goods_img/20220816/2717604/2717604_16726273467586_500.jpg"
            },
            {
                "title": "EE FLY NEC",
                "big_category": "주얼리",
                "small_category": "목걸이/펜던트",
                "item_hashtags": [
                    "목걸이",
                    "나비목걸이",
                    "데일리",
                    "패션",
                    "남녀공용",
                    "홀리데이"
                ],
                "image_url": "https://image.msscdn.net/images/goods_img/20200611/1481590/1481590_2_500.jpg"
            }
        ]
    },
    {
        "title": "올 블랙 스타일링",
        "styling_date": "2022.10.04",
        "view_num": 1438,
        "styling_txt": "리본 디테일이 매력적인 미니 원피스와 트렌치코트를 코디하고 앵클부츠로 완성한 로맨틱 룩",
        "image_url": "https://image.msscdn.net/images/codimap/detail/19023/detail_19023_1_500.jpg?202402142102",
        "item_urls": [
            "https://www.musinsa.com/app/goods/2381936",
            "https://www.musinsa.com/app/goods/2542041",
            "https://www.musinsa.com/app/goods/2752973",
            "https://www.musinsa.com/app/goods/2693517"
        ],
        "hashtags": [],
        "style_tag": "로맨틱",
        "item_list": [
            {
                "title": "여성 미드 렝스 켄싱턴 헤리티지 트렌지 코트 - 블랙 / 8045783",
                "big_category": "아우터",
                "small_category": "환절기 코트",
                "item_hashtags": [
                    "outique",
                    "티크",
                    "품 구분",
                    "티크 상품",
                    "신사 부티크는 프리미엄 디자이너 브랜드의 상품을 무신사만의 안목으로 엄선하여 제안하는 하이엔드 전문관입니다. 최근 글로벌에서 주목받는 브랜드부터 럭셔리 브랜드까지 이전에 없던 무신사의 폭넓은 큐레이션을 경험하세요."
                ],
                "image_url": "https://image.msscdn.net/images/goods_img/20220223/2381936/2381936_1_500.jpg"
            },
            {
                "title": "여성 클래식 랩 원피스 - 블랙 / N1019BK",
                "big_category": "원피스",
                "small_category": "미니 원피스",
                "item_hashtags": [
                    "outique",
                    "티크",
                    "품 구분",
                    "티크 상품",
                    "신사 부티크는 프리미엄 디자이너 브랜드의 상품을 무신사만의 안목으로 엄선하여 제안하는 하이엔드 전문관입니다. 최근 글로벌에서 주목받는 브랜드부터 럭셔리 브랜드까지 이전에 없던 무신사의 폭넓은 큐레이션을 경험하세요."
                ],
                "image_url": "https://image.msscdn.net/images/goods_img/20220504/2542041/2542041_1_500.jpg"
            },
            {
                "title": "여성 미니 글램 슬램 플랩 숄더백 - 블랙 / SB3WG0041P4300T8013",
                "big_category": "여성 가방",
                "small_category": "숄더백",
                "item_hashtags": [
                    "outique",
                    "티크",
                    "품 구분",
                    "티크 상품",
                    "신사 부티크는 프리미엄 디자이너 브랜드의 상품을 무신사만의 안목으로 엄선하여 제안하는 하이엔드 전문관입니다. 최근 글로벌에서 주목받는 브랜드부터 럭셔리 브랜드까지 이전에 없던 무신사의 폭넓은 큐레이션을 경험하세요."
                ],
                "image_url": "https://image.msscdn.net/images/goods_img/20220830/2752973/2752973_1_500.jpg"
            },
            {
                "title": "여성 스무스 카프 레더 에스테 앵클 부츠 - 블랙 / 1660507EBBLKLBL",
                "big_category": "신발",
                "small_category": "부츠",
                "item_hashtags": [
                    "outique",
                    "티크",
                    "품 구분",
                    "티크 상품",
                    "신사 부티크는 프리미엄 디자이너 브랜드의 상품을 무신사만의 안목으로 엄선하여 제안하는 하이엔드 전문관입니다. 최근 글로벌에서 주목받는 브랜드부터 럭셔리 브랜드까지 이전에 없던 무신사의 폭넓은 큐레이션을 경험하세요."
                ],
                "image_url": "https://image.msscdn.net/images/goods_img/20220802/2693517/2693517_1_500.jpg"
            }
        ]
    },
    {
        "title": "따라 입어봐",
        "styling_date": "2022.10.04",
        "view_num": 1958,
        "styling_txt": "그래픽 프린팅이 돋보이는 스웨트셔츠와 데님 팬츠를 매치하고 스니커즈로 마무리한 캐주얼 룩",
        "image_url": "https://image.msscdn.net/images/codimap/detail/19022/detail_19022_1_500.jpg?202402142102",
        "item_urls": [
            "https://www.musinsa.com/app/goods/2688341",
            "https://www.musinsa.com/app/goods/2507945",
            "https://www.musinsa.com/app/goods/2355604"
        ],
        "hashtags": [],
        "style_tag": "캐주얼",
        "item_list": [
            {
                "title": "여성 트위스트 심 데님 팬츠 - 워시드 블루 / 221232741405",
                "big_category": "바지",
                "small_category": "데님 팬츠",
                "item_hashtags": [
                    "outique",
                    "티크",
                    "품 구분",
                    "티크 상품",
                    "신사 부티크는 프리미엄 디자이너 브랜드의 상품을 무신사만의 안목으로 엄선하여 제안하는 하이엔드 전문관입니다. 최근 글로벌에서 주목받는 브랜드부터 럭셔리 브랜드까지 이전에 없던 무신사의 폭넓은 큐레이션을 경험하세요."
                ],
                "image_url": "https://image.msscdn.net/images/goods_img/20220729/2688341/2688341_1_500.jpg"
            },
            {
                "title": "여성 쿠베토 펠레 그라나타 크로스백 - 블랙 / FW21BAGCUBPE02",
                "big_category": "여성 가방",
                "small_category": "크로스백",
                "item_hashtags": [
                    "outique",
                    "티크",
                    "품 구분",
                    "티크 상품",
                    "신사 부티크는 프리미엄 디자이너 브랜드의 상품을 무신사만의 안목으로 엄선하여 제안하는 하이엔드 전문관입니다. 최근 글로벌에서 주목받는 브랜드부터 럭셔리 브랜드까지 이전에 없던 무신사의 폭넓은 큐레이션을 경험하세요."
                ],
                "image_url": "https://image.msscdn.net/images/goods_img/20220421/2507945/2507945_1_500.jpg"
            },
            {
                "title": "여성 오버사이즈 스니커즈 - 화이트:핑크 / 553770WHGP79182",
                "big_category": "스니커즈",
                "small_category": "패션스니커즈화",
                "item_hashtags": [
                    "outique",
                    "티크",
                    "품 구분",
                    "티크 상품",
                    "신사 부티크는 프리미엄 디자이너 브랜드의 상품을 무신사만의 안목으로 엄선하여 제안하는 하이엔드 전문관입니다. 최근 글로벌에서 주목받는 브랜드부터 럭셔리 브랜드까지 이전에 없던 무신사의 폭넓은 큐레이션을 경험하세요."
                ],
                "image_url": "https://image.msscdn.net/images/goods_img/20220211/2355604/2355604_2_500.jpg"
            }
        ]
    },
    {
        "title": "집순이 체질",
        "styling_date": "2022.10.04",
        "view_num": 923,
        "styling_txt": "그래픽이 돋보이는 스웨트셔츠와 미디스커트를 코디하고 언더웨어로 완성한 홈 웨어",
        "image_url": "https://image.msscdn.net/images/codimap/detail/19021/detail_19021_1_500.jpg?202402142102",
        "item_urls": [
            "https://www.musinsa.com/app/goods/2346123",
            "https://www.musinsa.com/app/goods/2447437",
            "https://www.musinsa.com/app/goods/1281581"
        ],
        "hashtags": [],
        "style_tag": "홈웨어",
        "item_list": [
            {
                "title": "스탬프 더미 크루넥 [화이트 멜란지]",
                "big_category": "상의",
                "small_category": "맨투맨/스웨트셔츠",
                "item_hashtags": [
                    "로고맨투맨",
                    "오버핏맨투맨",
                    "루즈핏맨투맨",
                    "맨투맨티셔츠",
                    "맨투맨",
                    "스웨트셔츠",
                    "스웻셔츠",
                    "화이트"
                ],
                "image_url": "https://image.msscdn.net/images/goods_img/20220208/2346123/2346123_2_500.jpg"
            },
            {
                "title": "KURLI MODAL scrunchie/hairband_shine pink",
                "big_category": "주얼리",
                "small_category": "헤어 액세서리",
                "item_hashtags": [
                    "헤어곱창",
                    "캐주얼",
                    "곱창밴드",
                    "곱창",
                    "데일리",
                    "심플",
                    "스크런치"
                ],
                "image_url": "https://image.msscdn.net/images/goods_img/20220327/2447437/2447437_1_500.jpg"
            },
            {
                "title": "블루라이트 주문제작 本 블랙실버 S000763",
                "big_category": "선글라스/안경테",
                "small_category": "안경",
                "item_hashtags": [
                    "골드색안경",
                    "동그란안경",
                    "블루라이트안경",
                    "블루라이트차단안경",
                    "뿔테",
                    "안경",
                    "패션안경"
                ],
                "image_url": "https://image.msscdn.net/images/goods_img/20200128/1281581/1281581_2_500.png"
            }
        ]
    },
    {
        "title": "고급스러운 무드",
        "styling_date": "2022.10.04",
        "view_num": 736,
        "styling_txt": "심플한 무드의 로브와 언더웨어로 연출한 홈 웨어",
        "image_url": "https://image.msscdn.net/images/codimap/detail/19020/detail_19020_1_500.jpg?202402142102",
        "item_urls": [
            "https://www.musinsa.com/app/goods/492514",
            "https://www.musinsa.com/app/goods/2295526"
        ],
        "hashtags": [],
        "style_tag": "홈웨어",
        "item_list": [
            {
                "title": "룸&패브릭 스프레이[THEN]",
                "big_category": "뷰티",
                "small_category": "향수/탈취",
                "item_hashtags": [],
                "image_url": "https://image.msscdn.net/images/goods_img/20170302/492514/492514_1_500.jpg"
            },
            {
                "title": "에이치엠1 룸슬리퍼 실내화 아이보리",
                "big_category": "신발",
                "small_category": "슬리퍼",
                "item_hashtags": [
                    "룸슬리퍼",
                    "가죽실내화",
                    "슬리퍼추천",
                    "집들이선물",
                    "실내화",
                    "룸슈즈",
                    "슬리퍼"
                ],
                "image_url": "https://image.msscdn.net/images/goods_img/20220106/2295526/2295526_2_500.jpg"
            }
        ]
    },
    {
        "title": "디테일이 돋보여",
        "styling_date": "2022.10.04",
        "view_num": 540,
        "styling_txt": "레이스 디테일이 매력적인 파자마 셋업과 언더웨어로 연출한 홈 웨어",
        "image_url": "https://image.msscdn.net/images/codimap/detail/19019/detail_19019_1_500.jpg?202402142102",
        "item_urls": [
            "https://www.musinsa.com/app/goods/2636699",
            "https://www.musinsa.com/app/goods/2782079",
            "https://www.musinsa.com/app/goods/2634819"
        ],
        "hashtags": [],
        "style_tag": "홈웨어",
        "item_list": [
            {
                "title": "[DAILY] 데일리 노와이어 브라렛 팬티 세트 - 화이트",
                "big_category": "속옷",
                "small_category": "여성 속옷 세트",
                "item_hashtags": [
                    "여성속옷",
                    "여름",
                    "여자친구선물",
                    "브라렛",
                    "노와이어브라세트",
                    "심리스브라",
                    "브라팬티세트"
                ],
                "image_url": "https://image.msscdn.net/images/goods_img/20220628/2636699/2636699_16981127345143_500.jpg"
            },
            {
                "title": "다운라이크 쿠션솜 (50x50)",
                "big_category": "리빙",
                "small_category": "홈패브릭",
                "item_hashtags": [],
                "image_url": "https://image.msscdn.net/images/goods_img/20220908/2782079/2782079_1_500.jpg"
            },
            {
                "title": "레이지 룸슈즈 화이트",
                "big_category": "신발",
                "small_category": "슬리퍼",
                "item_hashtags": [
                    "편한슬리퍼",
                    "룸슈즈",
                    "슬리퍼",
                    "집들이선물",
                    "실내화",
                    "거실화",
                    "스웨이드",
                    "CHILLOUT"
                ],
                "image_url": "https://image.msscdn.net/images/goods_img/20220627/2634819/2634819_1_500.jpg"
            }
        ]
    },
    {
        "title": "집콕하는 날",
        "styling_date": "2022.10.04",
        "view_num": 1413,
        "styling_txt": "로고 디테일이 돋보이는 긴소매 티셔츠와 트레이닝 팬츠를 매치하고 언더웨어로 마무리한 홈 웨어",
        "image_url": "https://image.msscdn.net/images/codimap/detail/19018/detail_19018_1_500.jpg?202402142102",
        "item_urls": [
            "https://www.musinsa.com/app/goods/1551053",
            "https://www.musinsa.com/app/goods/2729694",
            "https://www.musinsa.com/app/goods/2729710",
            "https://www.musinsa.com/app/goods/1896200",
            "https://www.musinsa.com/app/goods/2739798"
        ],
        "hashtags": [],
        "style_tag": "홈웨어",
        "item_list": [
            {
                "title": "HEAVY-TERRY BALLOON SWEAT PANTS (Gray)",
                "big_category": "바지",
                "small_category": "트레이닝/조거 팬츠",
                "item_hashtags": [
                    "바지",
                    "벌룬팬츠",
                    "스웻팬츠",
                    "와이드팬츠",
                    "트레이닝",
                    "벌룬스웻팬츠",
                    "트레이닝팬츠"
                ],
                "image_url": "https://image.msscdn.net/images/goods_img/20200815/1551053/1551053_2_500.jpg"
            },
            {
                "title": "여성 엠보스드 아이콘 코튼 트라이앵글 브라_QF6990DA3",
                "big_category": "속옷",
                "small_category": "여성 속옷 상의",
                "item_hashtags": [
                    "CK",
                    "CKUFW22NEW",
                    "노와이어"
                ],
                "image_url": "https://image.msscdn.net/images/goods_img/20220819/2729694/2729694_1_500.jpg"
            },
            {
                "title": "여성 엠보스드 아이콘 코튼 AF 비키니 팬티_QF6993ADDA3",
                "big_category": "속옷",
                "small_category": "여성 속옷 하의",
                "item_hashtags": [
                    "CK",
                    "여성속옷",
                    "CKUFW22NEW",
                    "언더웨어",
                    "속옷",
                    "팬티",
                    "삼각팬티",
                    "비키니"
                ],
                "image_url": "https://image.msscdn.net/images/goods_img/20220819/2729710/2729710_1_500.jpg"
            },
            {
                "title": "프렌치 무광 꼬임집게핀 3COLORS",
                "big_category": "주얼리",
                "small_category": "헤어 액세서리",
                "item_hashtags": [
                    "헤어집게핀",
                    "집게핀",
                    "헤어핀",
                    "무광집게핀",
                    "꼬임집게핀",
                    "헤어바렛",
                    "헤어악세사리"
                ],
                "image_url": "https://image.msscdn.net/images/goods_img/20210413/1896200/1896200_16837848844310_500.jpg"
            },
            {
                "title": "[젤하드 케이스] 고양이 행성 입장권",
                "big_category": "디지털/테크",
                "small_category": "휴대폰",
                "item_hashtags": [
                    "고양이케이스",
                    "갤럭시케이스",
                    "핸드폰케이스",
                    "폰케이스",
                    "스마트폰케이스",
                    "아이폰케이스",
                    "고양이"
                ],
                "image_url": "https://image.msscdn.net/images/goods_img/20220824/2739798/2739798_1_500.jpg"
            }
        ]
    },
    {
        "title": "편안한 하루",
        "styling_date": "2022.10.04",
        "view_num": 880,
        "styling_txt": "스트라이프 패턴이 돋보이는 파자마 셋업과 언더웨어로 완성한 홈 웨어",
        "image_url": "https://image.msscdn.net/images/codimap/detail/19017/detail_19017_1_500.jpg?202402142102",
        "item_urls": [
            "https://www.musinsa.com/app/goods/2729869",
            "https://www.musinsa.com/app/goods/2693763",
            "https://www.musinsa.com/app/goods/2231644",
            "https://www.musinsa.com/app/goods/2212029"
        ],
        "hashtags": [],
        "style_tag": "홈웨어",
        "item_list": [
            {
                "title": "여성 A039 그린 긴소매 상하",
                "big_category": "속옷",
                "small_category": "홈웨어",
                "item_hashtags": [],
                "image_url": "https://image.msscdn.net/images/goods_img/20220819/2729869/2729869_1_500.jpg"
            },
            {
                "title": "프리라인 심리스 SET (브라1+팬티1)_4 Colors",
                "big_category": "속옷",
                "small_category": "여성 속옷 세트",
                "item_hashtags": [
                    "언더웨어아이템"
                ],
                "image_url": "https://image.msscdn.net/images/goods_img/20220802/2693763/2693763_1_500.jpg"
            },
            {
                "title": "벨벳 스크런치_7COLOR",
                "big_category": "주얼리",
                "small_category": "헤어 액세서리",
                "item_hashtags": [
                    "악세사리",
                    "헤어악세사리",
                    "곱창밴드",
                    "머리끈",
                    "스크런치",
                    "홀리데이"
                ],
                "image_url": "https://image.msscdn.net/images/goods_img/20211115/2231644/2231644_1_500.jpg"
            },
            {
                "title": "LITTLE FIRE COVY-IVORY(머그컵)",
                "big_category": "리빙",
                "small_category": "주방용품",
                "item_hashtags": [],
                "image_url": "https://image.msscdn.net/images/goods_img/20211102/2212029/2212029_1_500.jpg"
            }
        ]
    },
    {
        "title": "꾸안꾸가 대세",
        "styling_date": "2022.10.04",
        "view_num": 3159,
        "styling_txt": "레터링이 돋보이는 스웨트셔츠와 코튼 팬츠를 매치하고 블루종을 더해 완성한 캐주얼 룩",
        "image_url": "https://image.msscdn.net/images/codimap/detail/19016/detail_19016_1_500.jpg?202402142102",
        "item_urls": [
            "https://www.musinsa.com/app/goods/2702050",
            "https://www.musinsa.com/app/goods/1354131",
            "https://www.musinsa.com/app/goods/1143478",
            "https://www.musinsa.com/app/goods/2229292",
            "https://www.musinsa.com/app/goods/2689909"
        ],
        "hashtags": [],
        "style_tag": "캐주얼",
        "item_list": [
            {
                "title": "오버사이즈 블루종 레더 배색 바시티 자켓 점퍼 [카키]",
                "big_category": "아우터",
                "small_category": "블루종/MA-1",
                "item_hashtags": [
                    "정판매",
                    "신사 스토어를 포함한 제한된 판매처에서만 구매 가능한 상품입니다."
                ],
                "image_url": "https://image.msscdn.net/images/goods_img/20220805/2702050/2702050_1_500.jpg"
            },
            {
                "title": "V.S.C SWEAT(NAVY)_NAVY",
                "big_category": "상의",
                "small_category": "맨투맨/스웨트셔츠",
                "item_hashtags": [
                    "정판매",
                    "신사 스토어를 포함한 제한된 판매처에서만 구매 가능한 상품입니다."
                ],
                "image_url": "https://image.msscdn.net/images/goods_img/20200317/1354131/1354131_16928428461922_500.jpg"
            },
            {
                "title": "고든 글라스(블랙)",
                "big_category": "선글라스/안경테",
                "small_category": "안경",
                "item_hashtags": [
                    "안경테",
                    "뿔테안경",
                    "아울렛",
                    "블루라이트차단안경",
                    "패션안경",
                    "남자안경",
                    "여자안경"
                ],
                "image_url": "https://image.msscdn.net/images/goods_img/20190905/1143478/1143478_2_500.jpg"
            },
            {
                "title": "패디드 보어백크로스 (블랙)",
                "big_category": "가방",
                "small_category": "메신저/크로스 백",
                "item_hashtags": [
                    "메신저백",
                    "여자크로스백",
                    "데일리가방",
                    "데일리백",
                    "남자크로스백",
                    "나일론백",
                    "크로스백"
                ],
                "image_url": "https://image.msscdn.net/images/goods_img/20211112/2229292/2229292_16831799898231_500.jpg"
            },
            {
                "title": "펜사토 베이지 아이보리",
                "big_category": "스니커즈",
                "small_category": "패션스니커즈화",
                "item_hashtags": [
                    "독일군",
                    "스니커즈",
                    "독일군스니커즈",
                    "독일군러너",
                    "캐주얼스니커즈",
                    "독일군시리즈"
                ],
                "image_url": "https://image.msscdn.net/images/goods_img/20220801/2689909/2689909_2_500.jpg"
            }
        ]
    },
    {
        "title": "미니멀 데이트 룩",
        "styling_date": "2022.10.04",
        "view_num": 3735,
        "styling_txt": "담백한 무드의 니트와 데님 팬츠를 스타일링하고 트러커 재킷과 첼시 부츠를 더해 연출한 댄디 룩",
        "image_url": "https://image.msscdn.net/images/codimap/detail/19015/detail_19015_1_500.jpg?202402142102",
        "item_urls": [
            "https://www.musinsa.com/app/goods/2680637",
            "https://www.musinsa.com/app/goods/2322454",
            "https://www.musinsa.com/app/goods/1811243"
        ],
        "hashtags": [],
        "style_tag": "댄디",
        "item_list": [
            {
                "title": "웨그너 블랙 데님 지퍼 자켓",
                "big_category": "아우터",
                "small_category": "트러커 재킷",
                "item_hashtags": [
                    "숏자켓",
                    "생지데님자켓",
                    "데님자켓",
                    "오버핏",
                    "청자켓",
                    "트러커",
                    "FW"
                ],
                "image_url": "https://image.msscdn.net/images/goods_img/20220725/2680637/2680637_2_500.jpg"
            },
            {
                "title": "다크니스 크랙 포인트 와이드 진",
                "big_category": "바지",
                "small_category": "데님 팬츠",
                "item_hashtags": [
                    "utlet",
                    "울렛",
                    "품 구분",
                    "울렛 상품",
                    "신사 스토어 아울렛은 무신사가 엄선한 인기 브랜드 상품을 높은 할인율의 특가로 만날 수 있는 전문관입니다. 스트릿, 캐주얼, 스포츠 패션 부터 럭셔리, 뷰티, 라이프 스타일 브랜드까지 다양한 상품을 언제나 아울렛 전용 혜택으로 제공합니다."
                ],
                "image_url": "https://image.msscdn.net/images/goods_img/20220124/2322454/2322454_17011538126566_500.jpg"
            },
            {
                "title": "라이트 체인 팔찌",
                "big_category": "주얼리",
                "small_category": "팔찌",
                "item_hashtags": [
                    "여자팔찌",
                    "체인팔찌",
                    "은팔찌",
                    "데일리팔찌",
                    "레이어드팔찌",
                    "써지컬스틸팔찌",
                    "남자팔찌"
                ],
                "image_url": "https://image.msscdn.net/images/goods_img/20210223/1811243/1811243_1_500.jpg"
            }
        ]
    },
    {
        "title": "추천하는 코디",
        "styling_date": "2022.10.04",
        "view_num": 3370,
        "styling_txt": "절개 디테일이 돋보이는 후드 티셔츠와 코튼 팬츠를 코디하고 스니커즈로 포인트를 더한 캐주얼 룩",
        "image_url": "https://image.msscdn.net/images/codimap/detail/19014/detail_19014_1_500.jpg?202402142102",
        "item_urls": [
            "https://www.musinsa.com/app/goods/2712038",
            "https://www.musinsa.com/app/goods/2754568",
            "https://www.musinsa.com/app/goods/2356711",
            "https://www.musinsa.com/app/goods/2593468",
            "https://www.musinsa.com/app/goods/2726322"
        ],
        "hashtags": [],
        "style_tag": "캐주얼",
        "item_list": [
            {
                "title": "PHYPS® WASHING DENIM JACKET BLACK",
                "big_category": "아우터",
                "small_category": "트러커 재킷",
                "item_hashtags": [
                    "utlet",
                    "울렛",
                    "품 구분",
                    "울렛 상품",
                    "신사 스토어 아울렛은 무신사가 엄선한 인기 브랜드 상품을 높은 할인율의 특가로 만날 수 있는 전문관입니다. 스트릿, 캐주얼, 스포츠 패션 부터 럭셔리, 뷰티, 라이프 스타일 브랜드까지 다양한 상품을 언제나 아울렛 전용 혜택으로 제공합니다."
                ],
                "image_url": "https://image.msscdn.net/images/goods_img/20220811/2712038/2712038_1_500.jpg"
            },
            {
                "title": "슬로건 스티치 후디_애쉬 그레이",
                "big_category": "상의",
                "small_category": "후드 티셔츠",
                "item_hashtags": [
                    "utlet",
                    "울렛",
                    "품 구분",
                    "울렛 상품",
                    "신사 스토어 아울렛은 무신사가 엄선한 인기 브랜드 상품을 높은 할인율의 특가로 만날 수 있는 전문관입니다. 스트릿, 캐주얼, 스포츠 패션 부터 럭셔리, 뷰티, 라이프 스타일 브랜드까지 다양한 상품을 언제나 아울렛 전용 혜택으로 제공합니다."
                ],
                "image_url": "https://image.msscdn.net/images/goods_img/20220830/2754568/2754568_2_500.jpg"
            },
            {
                "title": "Typeservice Web Cap [Black]",
                "big_category": "모자",
                "small_category": "캡/야구 모자",
                "item_hashtags": [
                    "정판매",
                    "신사 스토어를 포함한 제한된 판매처에서만 구매 가능한 상품입니다."
                ],
                "image_url": "https://image.msscdn.net/images/goods_img/20220213/2356711/2356711_2_500.jpg"
            },
            {
                "title": "[EVOKE LINE] 미니멀 호보 나일론 메신저백 L size [BLACK]",
                "big_category": "가방",
                "small_category": "메신저/크로스 백",
                "item_hashtags": [
                    "정판매",
                    "신사 스토어를 포함한 제한된 판매처에서만 구매 가능한 상품입니다."
                ],
                "image_url": "https://image.msscdn.net/images/goods_img/20220531/2593468/2593468_1_500.png"
            },
            {
                "title": "스케이트 하이 - (옴브레) 블랙:마쉬멜로우 / VN0A7Q5N1KP1",
                "big_category": "스니커즈",
                "small_category": "캔버스/단화",
                "item_hashtags": [
                    "스케이트하이",
                    "하이탑",
                    "옴브레운동화",
                    "옴브레스니커즈",
                    "옴브레"
                ],
                "image_url": "https://image.msscdn.net/images/goods_img/20220818/2726322/2726322_1_500.jpg"
            }
        ]
    },
    {
        "title": "편하고 힙하게",
        "styling_date": "2022.10.04",
        "view_num": 3840,
        "styling_txt": "유니크한 그래픽이 돋보이는 후드 티셔츠와 조거 팬츠를 매치하고 볼캡으로 마무리한 스트릿 룩",
        "image_url": "https://image.msscdn.net/images/codimap/detail/19013/detail_19013_1_500.jpg?202402142102",
        "item_urls": [
            "https://www.musinsa.com/app/goods/2739585",
            "https://www.musinsa.com/app/goods/2384630",
            "https://www.musinsa.com/app/goods/2681467"
        ],
        "hashtags": [],
        "style_tag": "스트릿",
        "item_list": [
            {
                "title": "Multi Color Nylon Windbreaker [CHARCOAL]",
                "big_category": "아우터",
                "small_category": "나일론/코치 재킷",
                "item_hashtags": [
                    "윈드브레이커",
                    "바람막이",
                    "오버사이즈",
                    "오버핏",
                    "캐주얼",
                    "스트릿",
                    "나일론자켓",
                    "22FW",
                    "고프코어"
                ],
                "image_url": "https://image.msscdn.net/images/goods_img/20220824/2739585/2739585_1_500.jpg"
            },
            {
                "title": "VELOCITY TRUCKER (BLACK)",
                "big_category": "모자",
                "small_category": "캡/야구 모자",
                "item_hashtags": [
                    "정판매",
                    "신사 스토어를 포함한 제한된 판매처에서만 구매 가능한 상품입니다."
                ],
                "image_url": "https://image.msscdn.net/images/goods_img/20220224/2384630/2384630_16746957509755_500.jpg"
            },
            {
                "title": "535 링크 실버 팔찌 스네이크 버클",
                "big_category": "주얼리",
                "small_category": "팔찌",
                "item_hashtags": [
                    "실버",
                    "실버팔찌",
                    "패션팔찌",
                    "남자팔찌",
                    "체인팔찌",
                    "레이어드팔찌",
                    "은팔찌"
                ],
                "image_url": "https://image.msscdn.net/images/goods_img/20220725/2681467/2681467_1_500.jpg"
            }
        ]
    },
    {
        "title": "가을 남자",
        "styling_date": "2022.10.04",
        "view_num": 4520,
        "styling_txt": "깔끔한 무드의 트렌치코트와 슬랙스를 코디하고 브리프케이스로 완성한 포멀 룩",
        "image_url": "https://image.msscdn.net/images/codimap/detail/19012/detail_19012_1_500.jpg?202402142102",
        "item_urls": [
            "https://www.musinsa.com/app/goods/1269066",
            "https://www.musinsa.com/app/goods/1293166",
            "https://www.musinsa.com/app/goods/1951470",
            "https://www.musinsa.com/app/goods/2504689",
            "https://www.musinsa.com/app/goods/2397119",
            "https://www.musinsa.com/app/goods/2509462",
            "https://www.musinsa.com/app/goods/2056061"
        ],
        "hashtags": [],
        "style_tag": "비즈니스캐주얼",
        "item_list": [
            {
                "title": "오버사이즈 트렌치 코트 BLACK",
                "big_category": "아우터",
                "small_category": "환절기 코트",
                "item_hashtags": [
                    "정판매",
                    "신사 스토어를 포함한 제한된 판매처에서만 구매 가능한 상품입니다."
                ],
                "image_url": "https://image.msscdn.net/images/goods_img/20200113/1269066/1269066_16928568810552_500.jpg"
            },
            {
                "title": "미니멀 브이넥 니트 베스트 블랙",
                "big_category": "아우터",
                "small_category": "베스트",
                "item_hashtags": [
                    "신사 단독",
                    "신사 스토어에서만 단독 판매하는 상품입니다."
                ],
                "image_url": "https://image.msscdn.net/images/goods_img/20200205/1293166/1293166_2_500.jpg"
            },
            {
                "title": "시티보이 보트자수 옥스포드 오버핏 셔츠 (WHITE)",
                "big_category": "상의",
                "small_category": "셔츠/블라우스",
                "item_hashtags": [
                    "정판매",
                    "신사 스토어를 포함한 제한된 판매처에서만 구매 가능한 상품입니다."
                ],
                "image_url": "https://image.msscdn.net/images/goods_img/20210514/1951470/1951470_16808462740425_500.jpg"
            },
            {
                "title": "세미 와이드 핏 울 슬랙스_DARK GREY",
                "big_category": "바지",
                "small_category": "슈트 팬츠/슬랙스",
                "item_hashtags": [
                    "정판매",
                    "신사 스토어를 포함한 제한된 판매처에서만 구매 가능한 상품입니다."
                ],
                "image_url": "https://image.msscdn.net/images/goods_img/20220420/2504689/2504689_1_500.png"
            },
            {
                "title": "남성메탈시계 F5201WH",
                "big_category": "시계",
                "small_category": "쿼츠 아날로그",
                "item_hashtags": [
                    "남자시계",
                    "패션시계",
                    "손목시계",
                    "데일리시계",
                    "남성손목시계",
                    "출근룩",
                    "캐주얼시계"
                ],
                "image_url": "https://image.msscdn.net/images/goods_img/20220304/2397119/2397119_1_500.jpg"
            },
            {
                "title": "소가죽 브리프케이스 서류가방 T1080",
                "big_category": "가방",
                "small_category": "브리프케이스",
                "item_hashtags": [
                    "출근룩",
                    "가죽",
                    "레더",
                    "데일리",
                    "남성",
                    "남자서류가방",
                    "서류가방"
                ],
                "image_url": "https://image.msscdn.net/images/goods_img/20220422/2509462/2509462_1_500.jpg"
            },
            {
                "title": "제리코 로퍼 BK",
                "big_category": "신발",
                "small_category": "로퍼",
                "item_hashtags": [
                    "수제화",
                    "출근룩",
                    "편안한",
                    "남자신발",
                    "남자로퍼"
                ],
                "image_url": "https://image.msscdn.net/images/goods_img/20210810/2056061/2056061_1_500.jpg"
            }
        ]
    },
    {
        "title": "즐겨 입는 패션",
        "styling_date": "2022.10.04",
        "view_num": 3315,
        "styling_txt": "로고 플레이가 돋보이는 스웨트셔츠와 데님 팬츠를 매치하고 볼캡을 더해 연출한 캐주얼 룩",
        "image_url": "https://image.msscdn.net/images/codimap/detail/19011/detail_19011_1_500.jpg?202402142102",
        "item_urls": [
            "https://www.musinsa.com/app/goods/1352242",
            "https://www.musinsa.com/app/goods/2623237",
            "https://www.musinsa.com/app/goods/2271789",
            "https://www.musinsa.com/app/goods/2748558"
        ],
        "hashtags": [],
        "style_tag": "캐주얼",
        "item_list": [
            {
                "title": "Bold Logo Pigment Sweatshirts GYD",
                "big_category": "상의",
                "small_category": "맨투맨/스웨트셔츠",
                "item_hashtags": [
                    "정판매",
                    "신사 스토어를 포함한 제한된 판매처에서만 구매 가능한 상품입니다."
                ],
                "image_url": "https://image.msscdn.net/images/goods_img/20200316/1352242/1352242_1_500.jpg"
            },
            {
                "title": "투 턱 웨이브 데님 팬츠 - 인디고",
                "big_category": "바지",
                "small_category": "데님 팬츠",
                "item_hashtags": [
                    "정판매",
                    "신사 스토어를 포함한 제한된 판매처에서만 구매 가능한 상품입니다."
                ],
                "image_url": "https://image.msscdn.net/images/goods_img/20220620/2623237/2623237_2_500.jpg"
            },
            {
                "title": "어센틱 메신저백 블랙",
                "big_category": "가방",
                "small_category": "메신저/크로스 백",
                "item_hashtags": [
                    "가방",
                    "메신저백",
                    "가방추천",
                    "신학기가방",
                    "크로스백",
                    "신학기",
                    "이십세들리뷰상품",
                    "젠더리스"
                ],
                "image_url": "https://image.msscdn.net/images/goods_img/20211217/2271789/2271789_17011510997651_500.jpg"
            },
            {
                "title": "DIVE PRO HI (BLACK)",
                "big_category": "스니커즈",
                "small_category": "캔버스/단화",
                "item_hashtags": [
                    "정판매",
                    "신사 스토어를 포함한 제한된 판매처에서만 구매 가능한 상품입니다."
                ],
                "image_url": "https://image.msscdn.net/images/goods_img/20220829/2748558/2748558_1_500.png"
            }
        ]
    },
    {
        "title": "뉴트럴 톤의 매력",
        "styling_date": "2022.10.04",
        "view_num": 2394,
        "styling_txt": "그래픽이 돋보이는 스웨트셔츠와 코튼 팬츠를 코디하고 스니커즈로 마무리한 캐주얼 룩",
        "image_url": "https://image.msscdn.net/images/codimap/detail/19010/detail_19010_1_500.jpg?202402142102",
        "item_urls": [
            "https://www.musinsa.com/app/goods/2680639",
            "https://www.musinsa.com/app/goods/2382032",
            "https://www.musinsa.com/app/goods/2283420",
            "https://www.musinsa.com/app/goods/2682871"
        ],
        "hashtags": [],
        "style_tag": "캐주얼",
        "item_list": [
            {
                "title": "웨그너 화이트 데님 지퍼 자켓",
                "big_category": "아우터",
                "small_category": "트러커 재킷",
                "item_hashtags": [
                    "오버핏자켓",
                    "데님자켓",
                    "청자켓",
                    "숏자켓",
                    "FW",
                    "트러커자켓"
                ],
                "image_url": "https://image.msscdn.net/images/goods_img/20220725/2680639/2680639_2_500.jpg"
            },
            {
                "title": "MODOO PANTS 모두바지 (Beige)",
                "big_category": "바지",
                "small_category": "코튼 팬츠",
                "item_hashtags": [
                    "utlet",
                    "울렛",
                    "품 구분",
                    "울렛 상품",
                    "신사 스토어 아울렛은 무신사가 엄선한 인기 브랜드 상품을 높은 할인율의 특가로 만날 수 있는 전문관입니다. 스트릿, 캐주얼, 스포츠 패션 부터 럭셔리, 뷰티, 라이프 스타일 브랜드까지 다양한 상품을 언제나 아울렛 전용 혜택으로 제공합니다."
                ],
                "image_url": "https://image.msscdn.net/images/goods_img/20220224/2382032/2382032_4_500.jpg"
            },
            {
                "title": "COSMO_BK",
                "big_category": "선글라스/안경테",
                "small_category": "안경",
                "item_hashtags": [
                    "안경",
                    "안경테",
                    "뿔테",
                    "하금테",
                    "남자안경",
                    "여자안경",
                    "동글이"
                ],
                "image_url": "https://image.msscdn.net/images/goods_img/20211227/2283420/2283420_2_500.jpg"
            },
            {
                "title": "멕시코 66 VIN SD 1183C015_101",
                "big_category": "스니커즈",
                "small_category": "패션스니커즈화",
                "item_hashtags": [
                    "멕시코66VINSD"
                ],
                "image_url": "https://image.msscdn.net/images/goods_img/20220726/2682871/2682871_1_500.jpg"
            }
        ]
    },
    {
        "title": "손이 가는 조합",
        "styling_date": "2022.10.04",
        "view_num": 3308,
        "styling_txt": "스트라이프 패턴이 돋보이는 긴소매 티셔츠와 데님 팬츠를 매치하고 백팩으로 완성한 캐주얼 룩",
        "image_url": "https://image.msscdn.net/images/codimap/detail/19009/detail_19009_1_500.jpg?202402142102",
        "item_urls": [
            "https://www.musinsa.com/app/goods/2311620",
            "https://www.musinsa.com/app/goods/1275020",
            "https://www.musinsa.com/app/goods/2594090"
        ],
        "hashtags": [],
        "style_tag": "캐주얼",
        "item_list": [
            {
                "title": "8012 비건레더후드점퍼_블랙",
                "big_category": "아우터",
                "small_category": "레더/라이더스 재킷",
                "item_hashtags": [
                    "에코레더",
                    "아울렛",
                    "업데이트",
                    "바이크코어트렌드",
                    "레더"
                ],
                "image_url": "https://image.msscdn.net/images/goods_img/20220118/2311620/2311620_2_500.jpg"
            },
            {
                "title": "스트라이프 와펜 로고 롱슬리브 네이비그린",
                "big_category": "상의",
                "small_category": "긴소매 티셔츠",
                "item_hashtags": [
                    "남녀공용",
                    "로고",
                    "롱슬리브",
                    "스트라이프",
                    "오버핏"
                ],
                "image_url": "https://image.msscdn.net/images/goods_img/20200118/1275020/1275020_2_500.jpg"
            },
            {
                "title": "스케이트 로우 - 컨트래스트 화이트:블랙 / VN0A5KXDYB21",
                "big_category": "스니커즈",
                "small_category": "캔버스/단화",
                "item_hashtags": [
                    "utlet",
                    "울렛",
                    "품 구분",
                    "울렛 상품",
                    "신사 스토어 아울렛은 무신사가 엄선한 인기 브랜드 상품을 높은 할인율의 특가로 만날 수 있는 전문관입니다. 스트릿, 캐주얼, 스포츠 패션 부터 럭셔리, 뷰티, 라이프 스타일 브랜드까지 다양한 상품을 언제나 아울렛 전용 혜택으로 제공합니다."
                ],
                "image_url": "https://image.msscdn.net/images/goods_img/20220531/2594090/2594090_1_500.jpg"
            }
        ]
    },
    {
        "title": "데일리로 추천!",
        "styling_date": "2022.10.04",
        "view_num": 2052,
        "styling_txt": "레터링이 돋보이는 스웨트셔츠와 데님 팬츠를 매치하고 백팩을 더해 연출한 캐주얼 룩",
        "image_url": "https://image.msscdn.net/images/codimap/detail/19008/detail_19008_1_500.jpg?202402142102",
        "item_urls": [
            "https://www.musinsa.com/app/goods/2057259",
            "https://www.musinsa.com/app/goods/2348436",
            "https://www.musinsa.com/app/goods/2418266",
            "https://www.musinsa.com/app/goods/2353206"
        ],
        "hashtags": [],
        "style_tag": "캐주얼",
        "item_list": [
            {
                "title": "남성 더블하트 와펜 집업 후드 - 화이트 / P1T2942 (AZT2940512)",
                "big_category": "아우터",
                "small_category": "후드 집업",
                "item_hashtags": [
                    "outique",
                    "티크",
                    "품 구분",
                    "티크 상품",
                    "신사 부티크는 프리미엄 디자이너 브랜드의 상품을 무신사만의 안목으로 엄선하여 제안하는 하이엔드 전문관입니다. 최근 글로벌에서 주목받는 브랜드부터 럭셔리 브랜드까지 이전에 없던 무신사의 폭넓은 큐레이션을 경험하세요."
                ],
                "image_url": "https://image.msscdn.net/images/goods_img/20210811/2057259/2057259_1_500.jpg"
            },
            {
                "title": "공용 4G 트윌 볼캡 - 블랙 / BPZ022P0C4001",
                "big_category": "모자",
                "small_category": "캡/야구 모자",
                "item_hashtags": [
                    "outique",
                    "티크",
                    "품 구분",
                    "티크 상품",
                    "신사 부티크는 프리미엄 디자이너 브랜드의 상품을 무신사만의 안목으로 엄선하여 제안하는 하이엔드 전문관입니다. 최근 글로벌에서 주목받는 브랜드부터 럭셔리 브랜드까지 이전에 없던 무신사의 폭넓은 큐레이션을 경험하세요."
                ],
                "image_url": "https://image.msscdn.net/images/goods_img/20220209/2348436/2348436_2_500.jpg"
            },
            {
                "title": "남성 익스플로러 나일론 백팩 - 블랙 / 5032212VZ371000",
                "big_category": "가방",
                "small_category": "백팩",
                "item_hashtags": [
                    "outique",
                    "티크",
                    "품 구분",
                    "티크 상품",
                    "신사 부티크는 프리미엄 디자이너 브랜드의 상품을 무신사만의 안목으로 엄선하여 제안하는 하이엔드 전문관입니다. 최근 글로벌에서 주목받는 브랜드부터 럭셔리 브랜드까지 이전에 없던 무신사의 폭넓은 큐레이션을 경험하세요."
                ],
                "image_url": "https://image.msscdn.net/images/goods_img/20220315/2418266/2418266_1_500.jpg"
            },
            {
                "title": "남성 슈퍼스타 그린 힐탭 스니커즈 - 화이트 / GMF00102F00218010802",
                "big_category": "스니커즈",
                "small_category": "패션스니커즈화",
                "item_hashtags": [
                    "outique",
                    "티크",
                    "품 구분",
                    "티크 상품",
                    "신사 부티크는 프리미엄 디자이너 브랜드의 상품을 무신사만의 안목으로 엄선하여 제안하는 하이엔드 전문관입니다. 최근 글로벌에서 주목받는 브랜드부터 럭셔리 브랜드까지 이전에 없던 무신사의 폭넓은 큐레이션을 경험하세요."
                ],
                "image_url": "https://image.msscdn.net/images/goods_img/20220210/2353206/2353206_1_500.jpg"
            }
        ]
    }
]