[
    {
        "title": "나이스 샷!",
        "styling_date": "2022.01.07",
        "view_num": 1135,
        "styling_txt": "퍼플 컬러가 매력적인 스웨트셔츠와 미니스커트를 코디하고 플리스로 완성한 골프 룩",
        "image_url": "https://image.msscdn.net/images/codimap/detail/11068/detail_11068_1_500.jpg?202402141602",
        "item_urls": [
            "https://www.musinsa.com/app/goods/2235317",
            "https://www.musinsa.com/app/goods/2127927"
        ],
        "hashtags": [],
        "style_tag": "골프",
        "item_list": [
            {
                "title": "퍼플 퍼프 스웻 셔츠",
                "big_category": "스포츠/용품",
                "small_category": "상의",
                "item_hashtags": [
                    "골프",
                    "여자골프옷",
                    "여성골프웨어",
                    "골프맨투맨",
                    "골프웨어",
                    "맨투맨"
                ],
                "image_url": "https://image.msscdn.net/images/goods_img/20211116/2235317/2235317_2_500.jpg"
            },
            {
                "title": "[ASIA] Golf 여성 C로고 스트레치 폴리 스커트 (NORMAL NAVY) CKSK1F070N2",
                "big_category": "스포츠/용품",
                "small_category": "스커트",
                "item_hashtags": [
                    "여성컬렉션",
                    "LF챔골"
                ],
                "image_url": "https://image.msscdn.net/images/goods_img/20210913/2127927/2127927_1_500.jpg"
            }
        ]
    },
    {
        "title": "남다른 센스",
        "styling_date": "2022.01.07",
        "view_num": 719,
        "styling_txt": "레이스 디테일이 매력적인 카라 티셔츠와 미니스커트를 매치하고 플리스로 마무리한 골프 룩",
        "image_url": "https://image.msscdn.net/images/codimap/detail/11066/detail_11066_1_500.jpg?202402141602",
        "item_urls": [
            "https://www.musinsa.com/app/goods/2209136",
            "https://www.musinsa.com/app/goods/2189944",
            "https://www.musinsa.com/app/goods/2218655",
            "https://www.musinsa.com/app/goods/2223757",
            "https://www.musinsa.com/app/goods/1924943"
        ],
        "hashtags": [],
        "style_tag": "골프",
        "item_list": [
            {
                "title": "Sharp Pattern Fleece Jumper (Black)",
                "big_category": "아우터",
                "small_category": "플리스/뽀글이",
                "item_hashtags": [],
                "image_url": "https://image.msscdn.net/images/goods_img/20211101/2209136/2209136_1_500.jpg"
            },
            {
                "title": "여성 레이스 리본 PK (블랙)",
                "big_category": "스포츠/용품",
                "small_category": "상의",
                "item_hashtags": [],
                "image_url": "https://image.msscdn.net/images/goods_img/20211020/2189944/2189944_4_500.jpg"
            },
            {
                "title": "WARM PLEATED BANDING SKIRT W/INNER PANTS_Ivory",
                "big_category": "스포츠/용품",
                "small_category": "스커트",
                "item_hashtags": [
                    "치마바지",
                    "플리츠스커트",
                    "골프스커트",
                    "필드스커트",
                    "여자골프웨어",
                    "골프치마",
                    "밴딩스커트"
                ],
                "image_url": "https://image.msscdn.net/images/goods_img/20211104/2218655/2218655_1_500.jpg"
            },
            {
                "title": "솔리드 블랙 오버니 삭스",
                "big_category": "양말/레그웨어",
                "small_category": "양말",
                "item_hashtags": [
                    "블랙",
                    "골프양말",
                    "오버니삭스"
                ],
                "image_url": "https://image.msscdn.net/images/goods_img/20211109/2223757/2223757_3_500.jpg"
            },
            {
                "title": "누에보 콤비 스파이크리스 골프화",
                "big_category": "스포츠/용품",
                "small_category": "스포츠신발",
                "item_hashtags": [
                    "오버도즈골프화",
                    "스파이크리스골프화",
                    "남성골프화",
                    "오버도즈골프",
                    "골프화",
                    "스파이크리스",
                    "여성골프화",
                    "72시간11/25-11/27"
                ],
                "image_url": "https://image.msscdn.net/images/goods_img/20210428/1924943/1924943_7_500.jpg"
            }
        ]
    },
    {
        "title": "완벽한 조합",
        "styling_date": "2022.01.07",
        "view_num": 1080,
        "styling_txt": "와펜 포인트의 베스트와 미니스커트를 코디하고 플리스로 완성한 골프 룩",
        "image_url": "https://image.msscdn.net/images/codimap/detail/11065/detail_11065_1_500.jpg?202402141602",
        "item_urls": [
            "https://www.musinsa.com/app/goods/2255100",
            "https://www.musinsa.com/app/goods/2142694",
            "https://www.musinsa.com/app/goods/2195060",
            "https://www.musinsa.com/app/goods/2205992",
            "https://www.musinsa.com/app/goods/2206918",
            "https://www.musinsa.com/app/goods/2245970",
            "https://www.musinsa.com/app/goods/2205989"
        ],
        "hashtags": [],
        "style_tag": "골프",
        "item_list": [
            {
                "title": "FLEECE POCKET SHORT JACKET(SH1LTF332MT)",
                "big_category": "아우터",
                "small_category": "플리스/뽀글이",
                "item_hashtags": [],
                "image_url": "https://image.msscdn.net/images/goods_img/20211202/2255100/2255100_1_500.jpg"
            },
            {
                "title": "와펜 브이넥 공용 베스트 네이비 HF-TT1304NY",
                "big_category": "아우터",
                "small_category": "베스트",
                "item_hashtags": [
                    "헤일리골프",
                    "골프웨어",
                    "골프웨어추천",
                    "골프"
                ],
                "image_url": "https://image.msscdn.net/images/goods_img/20210923/2142694/2142694_16804901216115_500.jpg"
            },
            {
                "title": "여성 빅포켓 포인트 카라티(화이트)",
                "big_category": "스포츠/용품",
                "small_category": "상의",
                "item_hashtags": [
                    "카라티",
                    "빅포켓카라티",
                    "포켓카라티",
                    "여성카라티",
                    "민트카라티",
                    "카라티셔츠",
                    "골프카라티"
                ],
                "image_url": "https://image.msscdn.net/images/goods_img/20211024/2195060/2195060_1_500.jpg"
            },
            {
                "title": "High-Waist H Line Skirt_Navy",
                "big_category": "스포츠/용품",
                "small_category": "스커트",
                "item_hashtags": [
                    "MDPICK"
                ],
                "image_url": "https://image.msscdn.net/images/goods_img/20211028/2205992/2205992_1_500.jpg"
            },
            {
                "title": "베이직 반양피 양손 골프장갑 (Grey)",
                "big_category": "스포츠/용품",
                "small_category": "스포츠잡화",
                "item_hashtags": [
                    "72시간11/28-11/30"
                ],
                "image_url": "https://image.msscdn.net/images/goods_img/20211029/2206918/2206918_1_500.jpg"
            },
            {
                "title": "오버 니하이 삭스_네이비",
                "big_category": "양말/레그웨어",
                "small_category": "양말",
                "item_hashtags": [
                    "니삭스",
                    "여성양말",
                    "골프양말",
                    "골프웨어",
                    "여자양말",
                    "양말추천",
                    "골프양말추천"
                ],
                "image_url": "https://image.msscdn.net/images/goods_img/20211124/2245970/2245970_1_500.jpg"
            },
            {
                "title": "Spikeless Tassel Loafer_Black",
                "big_category": "스포츠/용품",
                "small_category": "스포츠신발",
                "item_hashtags": [],
                "image_url": "https://image.msscdn.net/images/goods_img/20211028/2205989/2205989_1_500.jpg"
            }
        ]
    },
    {
        "title": "아가일 포인트",
        "styling_date": "2022.01.07",
        "view_num": 1115,
        "styling_txt": "아가일 패턴이 돋보이는 카디건과 플리스를 매치하고 선 캡으로 마무리한 골프 룩",
        "image_url": "https://image.msscdn.net/images/codimap/detail/11064/detail_11064_1_500.jpg?202402141602",
        "item_urls": [
            "https://www.musinsa.com/app/goods/2252855",
            "https://www.musinsa.com/app/goods/2181144",
            "https://www.musinsa.com/app/goods/2255506",
            "https://www.musinsa.com/app/goods/1926462"
        ],
        "hashtags": [],
        "style_tag": "골프",
        "item_list": [
            {
                "title": "헤비보아 플리스 후드집업 아이보리",
                "big_category": "아우터",
                "small_category": "플리스/뽀글이",
                "item_hashtags": [
                    "플리스점퍼",
                    "점퍼",
                    "플리스",
                    "오버핏",
                    "아우터",
                    "후리스",
                    "후리스집업"
                ],
                "image_url": "https://image.msscdn.net/images/goods_img/20211130/2252855/2252855_1_500.jpg"
            },
            {
                "title": "Argyle Pattern Knit Cardigan_Navy",
                "big_category": "스포츠/용품",
                "small_category": "아우터",
                "item_hashtags": [],
                "image_url": "https://image.msscdn.net/images/goods_img/20211015/2181144/2181144_1_500.jpg"
            },
            {
                "title": "여성 하이웨스트 코듀로이 부츠컷 팬츠",
                "big_category": "스포츠/용품",
                "small_category": "하의",
                "item_hashtags": [
                    "부츠컷",
                    "골프팬츠",
                    "코듀로이팬츠",
                    "골프웨어",
                    "골프바지"
                ],
                "image_url": "https://image.msscdn.net/images/goods_img/20211202/2255506/2255506_1_500.jpg"
            },
            {
                "title": "W EVELYN LEATHER GLOVES_ORANGE",
                "big_category": "스포츠/용품",
                "small_category": "스포츠잡화",
                "item_hashtags": [
                    "글로브",
                    "골프웨어",
                    "골프용품",
                    "골프장갑",
                    "장갑",
                    "골프악세사리",
                    "가죽장갑"
                ],
                "image_url": "https://image.msscdn.net/images/goods_img/20210428/1926462/1926462_1_500.jpg"
            }
        ]
    },
    {
        "title": "트렌디한 디테일",
        "styling_date": "2022.01.07",
        "view_num": 684,
        "styling_txt": "퍼프소매가 돋보이는 니트와 미니스커트를 매치하고 숏 패딩으로 마무리한 골프 룩",
        "image_url": "https://image.msscdn.net/images/codimap/detail/11063/detail_11063_1_500.jpg?202402141602",
        "item_urls": [
            "https://www.musinsa.com/app/goods/2273898",
            "https://www.musinsa.com/app/goods/2268095"
        ],
        "hashtags": [],
        "style_tag": "골프",
        "item_list": [
            {
                "title": "21 FW 퀼팅 숏 패딩 (화이트)",
                "big_category": "아우터",
                "small_category": "숏패딩/숏헤비 아우터",
                "item_hashtags": [],
                "image_url": "https://image.msscdn.net/images/goods_img/20211220/2273898/2273898_1_500.jpg"
            },
            {
                "title": "3M THINSULATE QUILTED SKIRT + MUFFLER SET",
                "big_category": "스포츠/용품",
                "small_category": "스커트",
                "item_hashtags": [
                    "골프스커트",
                    "스커트",
                    "골프치마",
                    "패딩스커트",
                    "퀼팅스커트",
                    "패딩머플러",
                    "겨울골프"
                ],
                "image_url": "https://image.msscdn.net/images/goods_img/20211214/2268095/2268095_1_500.jpg"
            }
        ]
    },
    {
        "title": "데일리 골프 웨어",
        "styling_date": "2022.01.07",
        "view_num": 1156,
        "styling_txt": "로고 프린팅이 돋보이는 카라 티셔츠와 미니스커트를 코디하고 플리스로 완성한 골프 룩",
        "image_url": "https://image.msscdn.net/images/codimap/detail/11062/detail_11062_1_500.jpg?202402141602",
        "item_urls": [
            "https://www.musinsa.com/app/goods/1977498",
            "https://www.musinsa.com/app/goods/2096290",
            "https://www.musinsa.com/app/goods/2232775",
            "https://www.musinsa.com/app/goods/1924926"
        ],
        "hashtags": [],
        "style_tag": "골프",
        "item_list": [
            {
                "title": "여성 프리미엄 9부 상의 (블랙)",
                "big_category": "스포츠/용품",
                "small_category": "상의",
                "item_hashtags": [],
                "image_url": "https://image.msscdn.net/images/goods_img/20210601/1977498/1977498_1_500.jpg"
            },
            {
                "title": "플랩 장식 베이직 스커트",
                "big_category": "스포츠/용품",
                "small_category": "스커트",
                "item_hashtags": [
                    "골프",
                    "골프치마",
                    "골프스커트",
                    "스키니스커트"
                ],
                "image_url": "https://image.msscdn.net/images/goods_img/20210829/2096290/2096290_6_500.jpg"
            },
            {
                "title": "Logo Point Fleece Bucket Hat_White",
                "big_category": "스포츠/용품",
                "small_category": "스포츠모자",
                "item_hashtags": [],
                "image_url": "https://image.msscdn.net/images/goods_img/20211115/2232775/2232775_4_500.jpg"
            },
            {
                "title": "누에보 화이트 스파이크리스 골프화",
                "big_category": "스포츠/용품",
                "small_category": "스포츠신발",
                "item_hashtags": [
                    "스파이크리스골프화",
                    "오버도즈골프화",
                    "여성골프화",
                    "골프화",
                    "남성골프화",
                    "스파이크리스",
                    "오버도즈골프",
                    "골프첫라운딩",
                    "72시간12/1-12/3"
                ],
                "image_url": "https://image.msscdn.net/images/goods_img/20210428/1924926/1924926_6_500.jpg"
            }
        ]
    }
]